respice/__init__.py
respice/analysis/Circuit.py
respice/analysis/MNAEquationStack.py
respice/analysis/TransientEFMSimulation.py
respice/analysis/TransientSimulation.py
respice/analysis/TransientSteadyStateEFMSimulation.py
respice/analysis/TransientSteadyStateSimulation.py
respice/analysis/UniqueEdgeMultiDiGraph.py
respice/analysis/__init__.py
respice/cachetools/LRUCache.py
respice/cachetools/__init__.py
respice/collections/OneToManyInvertibleMapping.py
respice/collections/__init__.py
respice/components/BipolarJunctionTransistor.py
respice/components/Branch.py
respice/components/Capacitance.py
respice/components/ComplementarySwitch.py
respice/components/Component.py
respice/components/CoupledInductance.py
respice/components/CurrentSourceAC.py
respice/components/CurrentSourceDC.py
respice/components/CurrentSourceHalfWaveAC.py
respice/components/CurrentSourcePWM.py
respice/components/CurrentSourceRectangular.py
respice/components/CurrentSourceSawtooth.py
respice/components/CurrentSourceTriangular.py
respice/components/Inductance.py
respice/components/LinearizedShockleyDiode.py
respice/components/Motor.py
respice/components/OperationalAmplifier.py
respice/components/PeriodicCurrentSource.py
respice/components/PeriodicSwitch.py
respice/components/PeriodicVoltageSource.py
respice/components/Resistance.py
respice/components/ShockleyDiode.py
respice/components/Switch.py
respice/components/SwitchPWM.py
respice/components/SwitchRectangular.py
respice/components/TwoTerminalCurrentComponent.py
respice/components/TwoTerminalVoltageComponent.py
respice/components/VoltageSourceAC.py
respice/components/VoltageSourceDC.py
respice/components/VoltageSourceHalfWaveAC.py
respice/components/VoltageSourcePWM.py
respice/components/VoltageSourceRectangular.py
respice/components/VoltageSourceSawtooth.py
respice/components/VoltageSourceTriangular.py
respice/components/__init__.py
respice/examples/LC.py
respice/examples/RC.py
respice/examples/RLC.py
respice/examples/__init__.py
respice-0.3.10.dist-info/LICENSE
respice-0.3.10.dist-info/METADATA
respice-0.3.10.dist-info/WHEEL
respice-0.3.10.dist-info/top_level.txt
respice-0.3.10.dist-info/RECORD
