Metadata-Version: 2.1
Name: respice
Version: 0.3.10
Summary: Flexible and easy to use non-linear transient electric circuit simulator.
Home-page: https://gitlab.com/Makman2/respice
Author: Mischa Krüger
Author-email: makmanx64@gmail.com
License: MIT
Project-URL: Bug Tracker, https://gitlab.com/Makman2/respice/issues
Project-URL: Source Code, https://gitlab.com/Makman2/respice/-/tree/master
Keywords: electronics circuit simulation non-linear transient steady-state time-domain
Platform: any
Classifier: Development Status :: 3 - Alpha
Classifier: Intended Audience :: Education
Classifier: Intended Audience :: Science/Research
Classifier: Programming Language :: Python :: 3.8
Classifier: Programming Language :: Python :: 3.9
Classifier: Programming Language :: Python :: 3.10
Classifier: Programming Language :: Python :: 3.11
Classifier: Programming Language :: Python :: 3.12
Classifier: Natural Language :: English
Classifier: Topic :: Scientific/Engineering :: Electronic Design Automation (EDA)
Classifier: Topic :: Scientific/Engineering :: Physics
Requires-Python: >=3.7
License-File: LICENSE
Requires-Dist: numpy >=1.16.3
Requires-Dist: networkx ~=2.3
Requires-Dist: scipy >=1.2.1
Requires-Dist: indexed ~=1.0
Requires-Dist: ordered-set ~=4.1.0
Provides-Extra: docs
Requires-Dist: sphinx ~=4.5.0 ; extra == 'docs'
Provides-Extra: interactive
Requires-Dist: pint ~=0.16.1 ; extra == 'interactive'
Requires-Dist: plotly ~=4.0 ; extra == 'interactive'
Requires-Dist: pandas >=1.0 ; extra == 'interactive'
Requires-Dist: rich ~=9.0 ; extra == 'interactive'
